{
  "configVersion": 1,
  "timestamp": 1624383124668,
  "index": "./index.html",
  "assetGroups": [
    {
      "name": "app",
      "installMode": "prefetch",
      "updateMode": "prefetch",
      "cacheQueryOptions": {
        "ignoreVary": true
      },
      "urls": [
        "./0.0d6b4a040efafbee14bc.js",
        "./2.46865a432fef78102344.js",
        "./6.7a49e71cedf3d1c5eac0.js",
        "./favicon.ico",
        "./index.html",
        "./main.d2c36f2452621cfc4694.js",
        "./manifest.webmanifest",
        "./polyfills.cc56d2b1d26ba44c0358.js",
        "./runtime.f1fda5c15f92e48719fd.js",
        "./scripts.ea5fcf5575ed4de9a3cc.js",
        "./styles.e068284aab4cfff3da35.css"
      ],
      "patterns": []
    },
    {
      "name": "assets",
      "installMode": "lazy",
      "updateMode": "prefetch",
      "cacheQueryOptions": {
        "ignoreVary": true
      },
      "urls": [
        "./assets/css/style.css",
        "./assets/i18n/en.json",
        "./assets/i18n/es.json",
        "./assets/icons/icon-128x128.png",
        "./assets/icons/icon-144x144.png",
        "./assets/icons/icon-152x152.png",
        "./assets/icons/icon-192x192.png",
        "./assets/icons/icon-384x384.png",
        "./assets/icons/icon-512x512.png",
        "./assets/icons/icon-72x72.png",
        "./assets/icons/icon-96x96.png",
        "./assets/images/.gitkeep",
        "./assets/images/comidas/empanadas.jpg",
        "./assets/images/comidas/hamburguesas.jpg",
        "./assets/images/comidas/lomitos.jpg",
        "./assets/images/comidas/milanesas.jpg",
        "./assets/images/comidas/pescados.jpg",
        "./assets/images/comidas/pizzas.jpg",
        "./assets/images/empanadas/arabes.jpg",
        "./assets/images/empanadas/criollas.jpg",
        "./assets/images/empanadas/pollo.jpg",
        "./assets/images/empanadas/salte単as.jpg",
        "./assets/images/favicon.ico",
        "./assets/images/footer.jpg",
        "./assets/images/hamburger-svgrepo-com.svg",
        "./assets/images/hamburguesas/cheddar.jpg",
        "./assets/images/hamburguesas/jalape単o.jpg",
        "./assets/images/hamburguesas/pan negro.jpg",
        "./assets/images/hamburguesas/yankee.jpg",
        "./assets/images/logo.png",
        "./assets/images/lomitos/bondiola-caramelizada-c.jpg",
        "./assets/images/lomitos/completo.jpg",
        "./assets/images/lomitos/mexicano.jpg",
        "./assets/images/lomitos/pollo.jpg",
        "./assets/images/pizzas/calabresa.jpg",
        "./assets/images/pizzas/doble-queso.jpg",
        "./assets/images/pizzas/especial.jpg",
        "./assets/images/pizzas/napolitana.jpg",
        "./fa-brands-400.216edb96b562c79adc09.svg",
        "./fa-brands-400.329a95a9172fdb2cccb4.woff",
        "./fa-brands-400.89a52ae1d02b86d61439.eot",
        "./fa-brands-400.9e138496e8f1719c6ebf.ttf",
        "./fa-brands-400.c1210e5ebe4344da5083.woff2",
        "./fa-regular-400.1017bce89c72f95bcf8e.ttf",
        "./fa-regular-400.19e27d348fefc21941e0.svg",
        "./fa-regular-400.3672264812746c3c7225.woff",
        "./fa-regular-400.4079ae2d2a15d0689568.eot",
        "./fa-regular-400.68c5af1f48e2bfca1e57.woff2",
        "./fa-solid-900.07c3313b24f7b1ca85ee.ttf",
        "./fa-solid-900.13de59f1a36b6cb4bca0.svg",
        "./fa-solid-900.ada6e6df937f7e5e8b79.woff2",
        "./fa-solid-900.c6ec080084769a6d8a34.woff",
        "./fa-solid-900.efbd5d20e407bbf85f2b.eot"
      ],
      "patterns": [
        "https:\\/\\/fonts\\.googleapis\\.com\\/.*",
        "https:\\/\\/use\\.fontawesome\\.com\\/.*",
        "https:\\/\\/code\\.jquery\\.com\\/.*",
        "https:\\/\\/cdnjs\\.cloudflare\\.com\\/.*",
        "https:\\/\\/maxcdn\\.bootstrapcdn\\.com\\/.*"
      ]
    }
  ],
  "dataGroups": [
    {
      "name": "pediya",
      "patterns": [
        "https:\\/\\/www\\.google\\.com\\/.*"
      ],
      "strategy": "performance",
      "maxSize": 20,
      "maxAge": 3600000,
      "timeoutMs": 5000,
      "cacheQueryOptions": {
        "ignoreVary": true
      },
      "version": 1
    }
  ],
  "hashTable": {
    "./0.0d6b4a040efafbee14bc.js": "a3273a167daa64d4f6307940b4710b80cfb2b08b",
    "./2.46865a432fef78102344.js": "62ac5ca7ded91223637f33e1636dadececf98b25",
    "./6.7a49e71cedf3d1c5eac0.js": "4a6a277f1a89615dad27391b588efe078bb1151f",
    "./assets/css/style.css": "ba8ab5a0280b953aa97435ff8946cbcbb2755a27",
    "./assets/i18n/en.json": "da39a3ee5e6b4b0d3255bfef95601890afd80709",
    "./assets/i18n/es.json": "1c0be9949a5ab46dd1824d91ca2ecde481c60096",
    "./assets/icons/icon-128x128.png": "f013e1104af6737867982c9f14e7144b2bd07f0a",
    "./assets/icons/icon-144x144.png": "8031a02696186dee6afbf0800d728cf7944401a7",
    "./assets/icons/icon-152x152.png": "3f8df075537a12cfd867978613ffd526413fcc2f",
    "./assets/icons/icon-192x192.png": "52350f0357c9720e3a8cb7a7cd7298ded4fd4ecc",
    "./assets/icons/icon-384x384.png": "0f2889ecb8a138b7db4f6bab89295c03054a477a",
    "./assets/icons/icon-512x512.png": "f1402e017cf99a0b868254219ba9be9a79ae72a1",
    "./assets/icons/icon-72x72.png": "cb16cbbc6d63ef7d1688336474e3d6e62dc2a31b",
    "./assets/icons/icon-96x96.png": "42de29fc721f089d2a61d74700a23f0a779f9ac2",
    "./assets/images/.gitkeep": "da39a3ee5e6b4b0d3255bfef95601890afd80709",
    "./assets/images/comidas/empanadas.jpg": "3fdb5533fd4c0d7e6ba1ea4b54179e94079af138",
    "./assets/images/comidas/hamburguesas.jpg": "e4f34936c57bd116a83a174f1d455971afb471a4",
    "./assets/images/comidas/lomitos.jpg": "b2437c21329bf696e1614dc6278a2558f9ea8e38",
    "./assets/images/comidas/milanesas.jpg": "d44f73b7cd5f776b28040370ac42f9c718522372",
    "./assets/images/comidas/pescados.jpg": "ad80b3e0fbc216b08f9074a36f16ea4e5c9ba601",
    "./assets/images/comidas/pizzas.jpg": "d6e532480a00ce3b1daaf96d397745ef67ef3679",
    "./assets/images/empanadas/arabes.jpg": "039e6e7af189b288cb63267e7d0a85c5c53698c1",
    "./assets/images/empanadas/criollas.jpg": "e46bc578bfe50add14d1ab0f0fd374cc79665d98",
    "./assets/images/empanadas/pollo.jpg": "fd22fa18a1f4eeb2509d2bd364cbd82293b20006",
    "./assets/images/empanadas/salte単as.jpg": "5618aa6679376f0e631662d44cacd5f8efe6d3cf",
    "./assets/images/favicon.ico": "07b630fd224b26de45aa62576a4eb89426fdb5ff",
    "./assets/images/footer.jpg": "effc814fcf2fcaadacf88dd03182798d2a9bd3a0",
    "./assets/images/hamburger-svgrepo-com.svg": "5bf72a25d05587d81271ae7e0526d97b408d3e23",
    "./assets/images/hamburguesas/cheddar.jpg": "d39af5cae00420d9147381da55f09d3c78b67f54",
    "./assets/images/hamburguesas/jalape単o.jpg": "dbd0ccea1fd314b9a4ca610df82eea1f106aa362",
    "./assets/images/hamburguesas/pan negro.jpg": "cd8192430d3777d6dd5531a880c9cb45d8b79a64",
    "./assets/images/hamburguesas/yankee.jpg": "c3a1f2f5259843c7668d699b47ca8d62f34a7c27",
    "./assets/images/logo.png": "858468214191924c9885e5072cbd3882b8c7eb3f",
    "./assets/images/lomitos/bondiola-caramelizada-c.jpg": "39ef2cab9b045f4b673cc94e3c18bb0eb906898e",
    "./assets/images/lomitos/completo.jpg": "333b6a15675ad58d083786b1f211f599b9e9e427",
    "./assets/images/lomitos/mexicano.jpg": "4fa73e1b427e5e518e1da84499f31ed914f7554f",
    "./assets/images/lomitos/pollo.jpg": "27ece638f4c243ae7a8a8b934476d7ab64ea49d2",
    "./assets/images/pizzas/calabresa.jpg": "4561a06f1c195f856d47050fefe991ce0ffe6725",
    "./assets/images/pizzas/doble-queso.jpg": "44317395740a26e760a91f1677548eae5873d831",
    "./assets/images/pizzas/especial.jpg": "f865bd771a63620146c41ee7113b7b85e0ad066e",
    "./assets/images/pizzas/napolitana.jpg": "465c3c1c91349044ca931259c7c12e1435fdabe3",
    "./fa-brands-400.216edb96b562c79adc09.svg": "24aff44d36f6c4a6a08230474b546b29641c75d6",
    "./fa-brands-400.329a95a9172fdb2cccb4.woff": "5f8cab91347c553c1eb87f9b527f6bee8a28e40d",
    "./fa-brands-400.89a52ae1d02b86d61439.eot": "a400bc89d3cb4d45a3b90791800587a1e4ebafa6",
    "./fa-brands-400.9e138496e8f1719c6ebf.ttf": "3fa2d67cef22da5c3f3eb5730c6afbd6fecf0372",
    "./fa-brands-400.c1210e5ebe4344da5083.woff2": "fce0da592a3e536d6d5df5b50cb513398d8c5161",
    "./fa-regular-400.1017bce89c72f95bcf8e.ttf": "7d849a3981a716e2ba4a84634bc57d0b8054a6a3",
    "./fa-regular-400.19e27d348fefc21941e0.svg": "8d0198777d4c6ff9c39a387f212b4ef732f70abb",
    "./fa-regular-400.3672264812746c3c7225.woff": "d33d8b5b15b7bba2cc17190dc685fe0a76d2989e",
    "./fa-regular-400.4079ae2d2a15d0689568.eot": "894064dfd376fc245fe654723d6c81f625e01363",
    "./fa-regular-400.68c5af1f48e2bfca1e57.woff2": "0447c6b10bbf73f97b23dcfd6e6a48510822cb6e",
    "./fa-solid-900.07c3313b24f7b1ca85ee.ttf": "c1b9fae262f42868c075ac865a8ab34920e20a2c",
    "./fa-solid-900.13de59f1a36b6cb4bca0.svg": "33fe5758f3992d8da2635c4fa230b54376dd18d1",
    "./fa-solid-900.ada6e6df937f7e5e8b79.woff2": "a9922842a120a7f1eaced667480c5e185a106d69",
    "./fa-solid-900.c6ec080084769a6d8a34.woff": "52751432ded489dfdf27fb1cf64c570c4c27a1d7",
    "./fa-solid-900.efbd5d20e407bbf85f2b.eot": "b18bdd10beee0a20231aa4c9ea11e84a9307a4fd",
    "./favicon.ico": "07b630fd224b26de45aa62576a4eb89426fdb5ff",
    "./index.html": "7d17eb8c39b2323d0fc01f5ed1d1a64711d4b8fb",
    "./main.d2c36f2452621cfc4694.js": "2731e8e51859ba8242f12ac12880be9bfdb0f917",
    "./manifest.webmanifest": "a38b8e1db059b6ff9493d8d6abf8fee7b4cb4492",
    "./polyfills.cc56d2b1d26ba44c0358.js": "74c31d3e548a2093d0cee7bdd10c3f127c7f0ae8",
    "./runtime.f1fda5c15f92e48719fd.js": "f96daa8fdeb3179afcd15fe4cd0d785b2fd9753d",
    "./scripts.ea5fcf5575ed4de9a3cc.js": "615c7d5f685b4a6d4d3f50e7889c07483499f79d",
    "./styles.e068284aab4cfff3da35.css": "5b08eced4b7e0ae8a404c4c407f6fe05433cd50d"
  },
  "navigationUrls": [
    {
      "positive": true,
      "regex": "^\\/.*$"
    },
    {
      "positive": false,
      "regex": "^\\/(?:.+\\/)?[^/]*\\.[^/]*$"
    },
    {
      "positive": false,
      "regex": "^\\/(?:.+\\/)?[^/]*__[^/]*$"
    },
    {
      "positive": false,
      "regex": "^\\/(?:.+\\/)?[^/]*__[^/]*\\/.*$"
    }
  ],
  "navigationRequestStrategy": "performance"
}